satlink/__init__.py
satlink/components/datalink.py
satlink/components/downlink.py
satlink/components/satellite.py
satlink/components/uplink.py
satlink-0.0.6.dist-info/METADATA
satlink-0.0.6.dist-info/WHEEL
satlink-0.0.6.dist-info/licenses/LICENSE
satlink-0.0.6.dist-info/RECORD
