Metadata-Version: 2.1
Name: satlink
Version: 0.0.6
Summary: A light web framework - originally developed as a project in Frameworks at HiØ, written with love in Python <3
Project-URL: Documentation, https://github.com/olejorga/satlink/wiki
Project-URL: Repository, https://github.com/olejorga/satlink
Author: olejorga
License-Expression: MIT
License-File: LICENSE
Classifier: License :: OSI Approved :: MIT License
Classifier: Operating System :: OS Independent
Classifier: Programming Language :: Python :: 3
Requires-Python: >=3.11
